notion/__init__.py
notion/block.py
notion/client.py
notion/collection.py
notion/logger.py
notion/maps.py
notion/markdown.py
notion/monitor.py
notion/operations.py
notion/records.py
notion/settings.py
notion/smoke_test.py
notion/space.py
notion/store.py
notion/user.py
notion/utils.py
notion/utils_ssl.py
notion_vzhd1701_fork-0.0.37.dist-info/LICENSE
notion_vzhd1701_fork-0.0.37.dist-info/METADATA
notion_vzhd1701_fork-0.0.37.dist-info/WHEEL
notion_vzhd1701_fork-0.0.37.dist-info/RECORD
