Metadata-Version: 2.1
Name: notion-vzhd1701-fork
Version: 0.0.37
Summary: Fork of https://github.com/jamalex/notion-py
Home-page: https://github.com/vzhd1701/notion-py
License: MIT
Author: Jamie Alexandre
Author-email: jamalex@gmail.com
Maintainer: vzhd1701
Maintainer-email: vzhd1701@gmail.com
Requires-Python: >=3.6,<4.0
Classifier: License :: OSI Approved :: MIT License
Classifier: Programming Language :: Python :: 3
Classifier: Programming Language :: Python :: 3.6
Classifier: Programming Language :: Python :: 3.7
Classifier: Programming Language :: Python :: 3.8
Classifier: Programming Language :: Python :: 3.9
Classifier: Programming Language :: Python :: 3.10
Classifier: Programming Language :: Python :: 3.11
Requires-Dist: bs4 (>=0.0.1,<0.0.2)
Requires-Dist: cached-property (>=1.5.2,<2.0.0)
Requires-Dist: commonmark (>=0.9.1,<0.10.0)
Requires-Dist: dictdiffer (>=0.9.0,<0.10.0)
Requires-Dist: python-slugify (>=6.1.2,<7.0.0)
Requires-Dist: ratelimit (>=2.2.1,<3.0.0)
Requires-Dist: requests (>=2.27.1,<3.0.0)
Requires-Dist: tzlocal (>=4.2,<5.0)
Project-URL: Repository, https://github.com/vzhd1701/notion-py
